daytona_mcp_interpreter/__init__.py
daytona_mcp_interpreter/server.py
mseep_daytona_mcp_interpreter-0.1.5.dist-info/licenses/LICENSE
mseep_daytona_mcp_interpreter-0.1.5.dist-info/METADATA
mseep_daytona_mcp_interpreter-0.1.5.dist-info/WHEEL
mseep_daytona_mcp_interpreter-0.1.5.dist-info/entry_points.txt
mseep_daytona_mcp_interpreter-0.1.5.dist-info/top_level.txt
mseep_daytona_mcp_interpreter-0.1.5.dist-info/RECORD
